Workbook

Sheet Main
A1: Какое озеро является самым глубоким в мире? | B1: Байкал | C1: Каспийское | D1: Виктория | E1: Танганьика | F1: 1 | G1: Озеро Байкал — самое глубокое в мире, его максимальная глубина составляет около 1642 метров.
A2: Какой химический элемент является основой органических соединений? | B2: Кремний | C2: Углерод | D2: Кислород | E2: Азот | F2: 2 | G2: Углерод образует основу органических соединений благодаря способности создавать длинные цепочки атомов.
A3: Какой город был столицей Древнего Египта в эпоху Нового царства? | B3: Мемфис | C3: Фивы | D3: Александрия | E3: Гиза | F3: 2 | G3: Фивы были столицей Египта в период Нового царства примерно с XVI по XI век до н. э.
A4: Какой отдел нервной системы отвечает за непроизвольные реакции? | B4: Соматическая | C4: Центральная | D4: Вегетативная | E4: Периферическая | F4: 3 | G4: Вегетативная нервная система регулирует непроизвольные процессы, такие как сердцебиение, дыхание и работа внутренних органов.
A5: Какая река считается самой длинной в Азии? | B5: Ганг | C5: Хуанхэ | D5: Янцзы | E5: Меконг | F5: 3 | G5: Длина реки Янцзы составляет около 6300 километров, что делает её самой длинной в Азии.
A6: Какое море считается самым глубоким в мире? | B6: Чёрное | C6: Средиземное | D6: Красное | E6: Карибское | F6: 1 | G6: Чёрное море имеет максимальную глубину около 2210 метров, что делает его самым глубоким морем Мирового океана.
A7: Какой материк имеет наибольшую среднюю высоту над уровнем моря? | B7: Африка | C7: Азия | D7: Южная Америка | E7: Антарктида | F7: 4 | G7: Средняя высота Антарктиды превышает 2000 метров из-за мощного ледникового покрова.
A8: Какой океан омывает восточное побережье Южной Америки? | B8: Тихий | C8: Индийский | D8: Атлантический | E8: Южный | F8: 3 | G8: Восточное побережье Южной Америки омывается Атлантическим океаном.
A9: Кто написал роман «1984»? | B9: Олдос Хаксли | C9: Джордж Оруэлл | D9: Рэй Брэдбери | E9: Франц Кафка | F9: 2 | G9: Антиутопический роман «1984» был опубликован Джорджем Оруэллом в 1949 году.
A10: Какой орган человека отвечает за детоксикацию крови? | B10: Почки | C10: Печень | D10: Сердце | E10: Лёгкие | F10: 2 | G10: Печень обезвреживает токсичные вещества и продукты обмена веществ.
A11: Какая страна первой приняла конституцию в современном виде? | B11: Франция | C11: Англия | D11: США | E11: Германия | F11: 3 | G11: Конституция США была принята в 1787 году и действует с поправками до сих пор.
A12: Как называется самая высокая точка Африки? | B12: Атлас | C12: Килиманджаро | D12: Драконовы горы | E12: Рувензори | F12: 2 | G12: Гора Килиманджаро имеет высоту около 5895 метров над уровнем моря.
... A26: Какой философ был учителем Александра Македонского? | B26: Платон | C26: Аристотель | D26: Сократ | E26: Эпикур | F26: 2 | G26: Аристотель обучал Александра Македонского философии и наукам в IV веке до н. э.
A27: В каком году человек впервые высадился на Луну? | B27: 1965 | C27: 1969 | D27: 1972 | E27: 1980 | F27: 2 | G27: Первая высадка человека на Луну состоялась в 1969 году в ходе миссии «Аполлон-11», когда Нил Армстронг ступил на поверхность спутника Земли.
A28: Какой химический элемент является самым распространённым во Вселенной? | B28: Кислород | C28: Водород | D28: Гелий | E28: Углерод | F28: 2 | G28: Водород составляет около 75 % всей видимой материи Вселенной и является основным компонентом звёзд.
A29: Какой материк полностью расположен в Южном полушарии? | B29: Южная Америка | C29: Африка | D29: Австралия | E29: Евразия | F29: 3 | G29: Австралия целиком находится в Южном полушарии и омывается Индийским и Тихим океанами.
A30: Какой прибор используется для измерения силы землетрясений? | B30: Термометр | C30: Сейсмограф | D30: Барометр | E30: Анемометр | F30: 2 | G30: Сейсмограф регистрирует колебания земной коры и позволяет определить силу и характеристики землетрясений.
A31: Какой материк является самым сухим на Земле? | B31: Африка | C31: Австралия | D31: Антарктида | E31: Южная Америка | F31: 3 | G31: Антарктида считается самым сухим материком, так как в её внутренних районах выпадает менее 50 мм осадков в год.
A32: Какое государство считается преемником Византийской империи? | B32: Болгария | C32: Османская империя | D32: Священная Римская империя | E32: Римская республика | F32: 2 | G32: После падения Константинополя в 1453 году Византийская империя была завоёвана Османской империей, которая унаследовала её территории.
A33: Какой химический элемент имеет атомный номер 1? | B33: Гелий | C33: Водород | D33: Литий | E33: Кислород | F33: 2 | G33: Водород — первый элемент таблицы Менделеева, его атом состоит из одного протона.
A34: Какой пролив соединяет Чёрное море с Мраморным? | B34: Дарданеллы | C34: Босфор | D34: Гибралтар | E34: Ла-Манш | F34: 2 | G34: Пролив Босфор соединяет Чёрное и Мраморное моря и проходит через территорию Стамбула.
A35: Какой орган человека отвечает за выработку инсулина? | B35: Печень | C35: Поджелудочная железа | D35: Желудок | E35: Селезёнка | F35: 2 | G35: Поджелудочная железа вырабатывает инсулин — гормон, регулирующий уровень сахара в крови.
A36: Какое государство имеет наибольшее население в мире? | B36: Индия | C36: США | D36: Китай | E36: Индонезия | F36: 1 | G36: Индия стала самой населённой страной мира в 2023 году, превысив население Китая.
A37: Кто был первым императором Римской империи? | B37: Юлий Цезарь | C37: Октавиан Август | D37: Нерон | E37: Калигула | F37: 2 | G37: Октавиан Август стал первым императором Рима в 27 году до н. э., положив начало Римской империи.
A38: Какой материк является самым маленьким по площади? | B38: Европа | C38: Антарктида | D38: Австралия | E38: Южная Америка | F38: 3 | G38: Австралия — самый маленький материк, её площадь составляет около 7,7 млн км².
A39: В каком веке произошло крещение Руси? | B39: IX | C39: X | D39: XI | E39: XII | F39: 2 | G39: Крещение Руси состоялось в 988 году при князе Владимире, что относится к X веку.
... A57: Как называется эпоха, последовавшая за Средневековьем? | B57: Античность | C57: Новое время | D57: Просвещение | E57: Возрождение | F57: 2 | G57: Новое время началось примерно в XV веке и связано с развитием науки, географическими открытиями и изменениями в обществе.

Sheet export
A1: Вопрос | B1: Вариант1 | C1: Вариант2 | D1: Вариант3 | E1: Вариант4 | F1: Индекс | G1: Пояснение
A2: =Main!A2 -> Какой химический элемент является основой органических соединений? | B2: =Main!B2 -> Кремний | C2: =Main!C2 -> Углерод | D2: =Main!D2 -> Кислород | E2: =Main!E2 -> Азот | F2: =Main!F2 -> 2 | G2: =Main!G2 -> Углерод образует основу органических соединений благодаря способности создавать длинные цепочки атомов.
A3: =Main!A3 -> Какой город был столицей Древнего Египта в эпоху Нового царства? | B3: =Main!B3 -> Мемфис | C3: =Main!C3 -> Фивы | D3: =Main!D3 -> Александрия | E3: =Main!E3 -> Гиза | F3: =Main!F3 -> 2 | G3: =Main!G3 -> Фивы были столицей Египта в период Нового царства примерно с XVI по XI век до н. э.
A4: =Main!A4 -> Какой отдел нервной системы отвечает за непроизвольные реакции? | B4: =Main!B4 -> Соматическая | C4: =Main!C4 -> Центральная | D4: =Main!D4 -> Вегетативная | E4: =Main!E4 -> Периферическая | F4: =Main!F4 -> 3 | G4: =Main!G4 -> Вегетативная нервная система регулирует непроизвольные процессы, такие как сердцебиение, дыхание и работа внутренних органов.
A5: =Main!A5 -> Какая река считается самой длинной в Азии? | B5: =Main!B5 -> Ганг | C5: =Main!C5 -> Хуанхэ | D5: =Main!D5 -> Янцзы | E5: =Main!E5 -> Меконг | F5: =Main!F5 -> 3 | G5: =Main!G5 -> Длина реки Янцзы составляет около 6300 километров, что делает её самой длинной в Азии.
A6: =Main!A6 -> Какое море считается самым глубоким в мире? | B6: =Main!B6 -> Чёрное | C6: =Main!C6 -> Средиземное | D6: =Main!D6 -> Красное | E6: =Main!E6 -> Карибское | F6: =Main!F6 -> 1 | G6: =Main!G6 -> Чёрное море имеет максимальную глубину около 2210 метров, что делает его самым глубоким морем Мирового океана.
A7: =Main!A7 -> Какой материк имеет наибольшую среднюю высоту над уровнем моря? | B7: =Main!B7 -> Африка | C7: =Main!C7 -> Азия | D7: =Main!D7 -> Южная Америка | E7: =Main!E7 -> Антарктида | F7: =Main!F7 -> 4 | G7: =Main!G7 -> Средняя высота Антарктиды превышает 2000 метров из-за мощного ледникового покрова.
A8: =Main!#REF! -> #REF! | B8: =Main!#REF! -> #REF! | C8: =Main!#REF! -> #REF! | D8: =Main!#REF! -> #REF! | E8: =Main!#REF! -> #REF! | F8: =Main!#REF! -> #REF! | G8: =Main!#REF! -> #REF!
A9: =Main!A8 -> Какой океан омывает восточное побережье Южной Америки? | B9: =Main!B8 -> Тихий | C9: =Main!C8 -> Индийский | D9: =Main!D8 -> Атлантический | E9: =Main!E8 -> Южный | F9: =Main!F8 -> 3 | G9: =Main!G8 -> Восточное побережье Южной Америки омывается Атлантическим океаном.
A10: =Main!A9 -> Кто написал роман «1984»? | B10: =Main!B9 -> Олдос Хаксли | C10: =Main!C9 -> Джордж Оруэлл | D10: =Main!D9 -> Рэй Брэдбери | E10: =Main!E9 -> Франц Кафка | F10: =Main!F9 -> 2 | G10: =Main!G9 -> Антиутопический роман «1984» был опубликован Джорджем Оруэллом в 1949 году.
A11: =Main!#REF! -> #REF! | B11: =Main!#REF! -> #REF! | C11: =Main!#REF! -> #REF! | D11: =Main!#REF! -> #REF! | E11: =Main!#REF! -> #REF! | F11: =Main!#REF! -> #REF! | G11: =Main!#REF! -> #REF!
A12: =Main!A10 -> Какой орган человека отвечает за детоксикацию крови? | B12: =Main!B10 -> Почки | C12: =Main!C10 -> Печень | D12: =Main!D10 -> Сердце | E12: =Main!E10 -> Лёгкие | F12: =Main!F10 -> 2 | G12: =Main!G10 -> Печень обезвреживает токсичные вещества и продукты обмена веществ.
A13: =Main!A11 -> Какая страна первой приняла конституцию в современном виде? | B13: =Main!B11 -> Франция | C13: =Main!C11 -> Англия | D13: =Main!D11 -> США | E13: =Main!E11 -> Германия | F13: =Main!F11 -> 3 | G13: =Main!G11 -> Конституция США была принята в 1787 году и действует с поправками до сих пор.
A14: =Main!A12 -> Как называется самая высокая точка Африки? | B14: =Main!B12 -> Атлас | C14: =Main!C12 -> Килиманджаро | D14: =Main!D12 -> Драконовы горы | E14: =Main!E12 -> Рувензори | F14: =Main!F12 -> 2 | G14: =Main!G12 -> Гора Килиманджаро имеет высоту около 5895 метров над уровнем моря.
A15: =Main!A13 -> Какой химический элемент обозначается символом Sn? | B15: =Main!B13 -> Сера | C15: =Main!C13 -> Свинец | D15: =Main!D13 -> Олово | E15: =Main!E13 -> Селен | F15: =Main!F13 -> 3 | G15: =Main!G13 -> Sn — химический символ олова, происходящий от латинского названия Stannum.
A16: =Main!A14 -> Какой материк пересекают оба тропика? | B16: =Main!B14 -> Африка | C16: =Main!C14 -> Южная Америка | D16: =Main!D14 -> Австралия | E16: =Main!E14 -> Евразия | F16: =Main!F14 -> 1 | G16: =Main!G14 -> Африка пересекается тропиком Рака и тропиком Козерога.
A17: =Main!A15 -> Какой писатель является автором романа «Процесс»? | B17: =Main!B15 -> Кафка | C17: =Main!C15 -> Камю | D17: =Main!D15 -> Манн | E17: =Main!E15 -> Гессе | F17: =Main!F15 -> 1 | G17: =Main!G15 -> Роман «Процесс» был написан Францем Кафкой и опубликован посмертно в 1925 году.
A18: =Main!A16 -> Как называется нижний слой атмосферы Земли? | B18: =Main!B16 -> Стратосфера | C18: =Main!C16 -> Мезосфера | D18: =Main!D16 -> Тропосфера | E18: =Main!E16 -> Ионосфера | F18: =Main!F16 -> 3 | G18: =Main!G16 -> Тропосфера простирается до высоты примерно 8–18 километров и содержит большую часть воздуха.
A19: =Main!#REF! -> #REF! | B19: =Main!#REF! -> #REF! | C19: =Main!#REF! -> #REF! | D19: =Main!#REF! -> #REF! | E19: =Main!#REF! -> #REF! | F19: =Main!#REF! -> #REF! | G19: =Main!#REF! -> #REF!
A20: =Main!A17 -> Какой металл используется в ядерной энергетике как топливо? | B20: =Main!B17 -> Плутоний | C20: =Main!C17 -> Железо | D20: =Main!D17 -> Медь | E20: =Main!E17 -> Цинк | F20: =Main!F17 -> 1 | G20: =Main!G17 -> Плутоний применяется как ядерное топливо в реакторах и энергетике.
A21: =Main!A18 -> Какое государство является самым маленьким в мире? | B21: =Main!B18 -> Монако | C21: =Main!C18 -> Ватикан | D21: =Main!D18 -> Сан-Марино | E21: =Main!E18 -> Лихтенштейн | F21: =Main!F18 -> 2 | G21: =Main!G18 -> Площадь Ватикана составляет около 0,44 квадратного километра.
A22: =Main!A19 -> Какой процесс лежит в основе работы тепловых двигателей? | B22: =Main!B19 -> Испарение | C22: =Main!C19 -> Горение | D22: =Main!D19 -> Конденсация | E22: =Main!E19 -> Осмос | F22: =Main!F19 -> 2 | G22: =Main!G19 -> Работа тепловых двигателей основана на выделении энергии при горении топлива.
A23: =Main!A20 -> Какой спутник является крупнейшим в Солнечной системе? | B23: =Main!B20 -> Титан | C23: =Main!C20 -> Ганимед | D23: =Main!D20 -> Луна | E23: =Main!E20 -> Ио | F23: =Main!F20 -> 2 | G23: =Main!G20 -> Ганимед — спутник Юпитера, его диаметр превышает 5200 километров.
A24: =Main!A21 -> Какой элемент необходим для работы щитовидной железы? | B24: =Main!B21 -> Кальций | C24: =Main!C21 -> Йод | D24: =Main!D21 -> Фосфор | E24: =Main!E21 -> Калий | F24: =Main!F21 -> 2 | G24: =Main!G21 -> Йод необходим для синтеза гормонов, регулирующих обмен веществ.
A25: =Main!A22 -> Какой город считается культурной столицей Италии эпохи Возрождения? | B25: =Main!B22 -> Рим | C25: =Main!C22 -> Венеция | D25: =Main!D22 -> Флоренция | E25: =Main!E22 -> Милан | F25: =Main!F22 -> 3 | G25: =Main!G22 -> Флоренция была центром искусства Возрождения в XV–XVI веках.
A26: =Main!A23 -> Какой отдел головного мозга участвует в формировании речи? | B26: =Main!B23 -> Мозжечок | C26: =Main!C23 -> Лобные доли | D26: =Main!D23 -> Теменные доли | E26: =Main!E23 -> Продолговатый мозг | F26: =Main!F23 -> 2 | G26: =Main!G23 -> Лобные доли головного мозга, в частности зона Брока, играют ключевую роль в формировании речи и контроле речевой активности.
A27: =Main!A24 -> Какой океан отделяет Африку от Южной Америки? | B27: =Main!B24 -> Тихий | C27: =Main!C24 -> Индийский | D27: =Main!D24 -> Атлантический | E27: =Main!E24 -> Южный | F27: =Main!F24 -> 3 | G27: =Main!G24 -> Атлантический океан расположен между Африкой и Южной Америкой.
A28: =Main!A25 -> Какой металл является основным компонентом бронзы? | B28: =Main!B25 -> Железо | C28: =Main!C25 -> Олово | D28: =Main!D25 -> Медь | E28: =Main!E25 -> Цинк | F28: =Main!F25 -> 3 | G28: =Main!G25 -> Бронза представляет собой сплав меди с добавлением олова.
A29: =Main!A26 -> Какой философ был учителем Александра Македонского? | B29: =Main!B26 -> Платон | C29: =Main!C26 -> Аристотель | D29: =Main!D26 -> Сократ | E29: =Main!E26 -> Эпикур | F29: =Main!F26 -> 2 | G29: =Main!G26 -> Аристотель обучал Александра Македонского философии и наукам в IV веке до н. э.
A30: =Main!A27 -> В каком году человек впервые высадился на Луну? | B30: =Main!B27 -> 1965 | C30: =Main!C27 -> 1969 | D30: =Main!D27 -> 1972 | E30: =Main!E27 -> 1980 | F30: =Main!F27 -> 2 | G30: =Main!G27 -> Первая высадка человека на Луну состоялась в 1969 году в ходе миссии «Аполлон-11», когда Нил Армстронг ступил на поверхность спутника Земли.
A31: =Main!A28 -> Какой химический элемент является самым распространённым во Вселенной? | B31: =Main!B28 -> Кислород | C31: =Main!C28 -> Водород | D31: =Main!D28 -> Гелий | E31: =Main!E28 -> Углерод | F31: =Main!F28 -> 2 | G31: =Main!G28 -> Водород составляет около 75 % всей видимой материи Вселенной и является основным компонентом звёзд.
... A40: =Main!A37 -> Кто был первым императором Римской империи? | B40: =Main!B37 -> Юлий Цезарь | C40: =Main!C37 -> Октавиан Август | D40: =Main!D37 -> Нерон | E40: =Main!E37 -> Калигула | F40: =Main!F37 -> 2 | G40: =Main!G37 -> Октавиан Август стал первым императором Рима в 27 году до н. э., положив начало Римской империи.
A41: =Main!#REF! -> #REF! | B41: =Main!#REF! -> #REF! | C41: =Main!#REF! -> #REF! | D41: =Main!#REF! -> #REF! | E41: =Main!#REF! -> #REF! | F41: =Main!#REF! -> #REF! | G41: =Main!#REF! -> #REF!
A42: =Main!A38 -> Какой материк является самым маленьким по площади? | B42: =Main!B38 -> Европа | C42: =Main!C38 -> Антарктида | D42: =Main!D38 -> Австралия | E42: =Main!E38 -> Южная Америка | F42: =Main!F38 -> 3 | G42: =Main!G38 -> Австралия — самый маленький материк, её площадь составляет около 7,7 млн км².
A43: =Main!A39 -> В каком веке произошло крещение Руси? | B43: =Main!B39 -> IX | C43: =Main!C39 -> X | D43: =Main!D39 -> XI | E43: =Main!E39 -> XII | F43: =Main!F39 -> 2 | G43: =Main!G39 -> Крещение Руси состоялось в 988 году при князе Владимире, что относится к X веку.
A44: =Main!A40 -> Какой металл является основным компонентом стали? | B44: =Main!B40 -> Алюминий | C44: =Main!C40 -> Медь | D44: =Main!D40 -> Железо | E44: =Main!E40 -> Никель | F44: =Main!F40 -> 3 | G44: =Main!G40 -> Сталь представляет собой сплав на основе железа с добавлением углерода.
A45: =Main!#REF! -> #REF! | B45: =Main!#REF! -> #REF! | C45: =Main!#REF! -> #REF! | D45: =Main!#REF! -> #REF! | E45: =Main!#REF! -> #REF! | F45: =Main!#REF! -> #REF! | G45: =Main!#REF! -> #REF!
A46: =Main!#REF! -> #REF! | B46: =Main!#REF! -> #REF! | C46: =Main!#REF! -> #REF! | D46: =Main!#REF! -> #REF! | E46: =Main!#REF! -> #REF! | F46: =Main!#REF! -> #REF! | G46: =Main!#REF! -> #REF!
A47: =Main!A41 -> Какой океан является самым холодным? | B47: =Main!B41 -> Тихий | C47: =Main!C41 -> Атлантический | D47: =Main!D41 -> Индийский | E47: =Main!E41 -> Северный Ледовитый | F47: =Main!F41 -> 4 | G47: =Main!G41 -> Северный Ледовитый океан имеет самые низкие средние температуры воды из-за полярного расположения.
A48: =Main!#REF! -> #REF! | B48: =Main!#REF! -> #REF! | C48: =Main!#REF! -> #REF! | D48: =Main!#REF! -> #REF! | E48: =Main!#REF! -> #REF! | F48: =Main!#REF! -> #REF! | G48: =Main!#REF! -> #REF!
A49: =Main!A42 -> Какой прибор используется для измерения влажности воздуха? | B49: =Main!B42 -> Барометр | C49: =Main!C42 -> Гигрометр | D49: =Main!D42 -> Манометр | E49: =Main!E42 -> Термометр | F49: =Main!F42 -> 2 | G49: =Main!G42 -> Гигрометр измеряет относительную влажность воздуха, важную для прогноза погоды.
A50: =Main!A43 -> Какое море является самым солёным в мире? | B50: =Main!B43 -> Красное | C50: =Main!C43 -> Мёртвое | D50: =Main!D43 -> Аравийское | E50: =Main!E43 -> Средиземное | F50: =Main!F43 -> 2 | G50: =Main!G43 -> Мёртвое море имеет солёность более 300 промилле (‰), что в несколько раз выше океанской.
A51: =Main!#REF! -> #REF! | B51: =Main!#REF! -> #REF! | C51: =Main!#REF! -> #REF! | D51: =Main!#REF! -> #REF! | E51: =Main!#REF! -> #REF! | F51: =Main!#REF! -> #REF! | G51: =Main!#REF! -> #REF!
A52: =Main!#REF! -> #REF! | B52: =Main!#REF! -> #REF! | C52: =Main!#REF! -> #REF! | D52: =Main!#REF! -> #REF! | E52: =Main!#REF! -> #REF! | F52: =Main!#REF! -> #REF! | G52: =Main!#REF! -> #REF!
A53: =Main!A44 -> Какой элемент необходим для образования костной ткани? | B53: =Main!B44 -> Железо | C53: =Main!C44 -> Йод | D53: =Main!D44 -> Кальций | E53: =Main!E44 -> Натрий | F53: =Main!F44 -> 3 | G53: =Main!G44 -> Кальций является основным элементом, обеспечивающим прочность костей и зубов.
A54: =Main!#REF! -> #REF! | B54: =Main!#REF! -> #REF! | C54: =Main!#REF! -> #REF! | D54: =Main!#REF! -> #REF! | E54: =Main!#REF! -> #REF! | F54: =Main!#REF! -> #REF! | G54: =Main!#REF! -> #REF!
A55: =Main!#REF! -> #REF! | B55: =Main!#REF! -> #REF! | C55: =Main!#REF! -> #REF! | D55: =Main!#REF! -> #REF! | E55: =Main!#REF! -> #REF! | F55: =Main!#REF! -> #REF! | G55: =Main!#REF! -> #REF!
A56: =Main!A45 -> Какой орган регулирует водный баланс организма? | B56: =Main!B45 -> Печень | C56: =Main!C45 -> Сердце | D56: =Main!D45 -> Почки | E56: =Main!E45 -> Лёгкие | F56: =Main!F45 -> 3 | G56: =Main!G45 -> Почки фильтруют кровь и регулируют количество воды и солей в организме.
A57: =Main!A46 -> Какой континент был открыт последним? | B57: =Main!B46 -> Австралия | C57: =Main!C46 -> Антарктида | D57: =Main!D46 -> Африка | E57: =Main!E46 -> Южная Америка | F57: =Main!F46 -> 2 | G57: =Main!G46 -> Антарктида была официально открыта в 1820 году русской экспедицией Беллинсгаузена и Лазарева.
A58: =Main!#REF! -> #REF! | B58: =Main!#REF! -> #REF! | C58: =Main!#REF! -> #REF! | D58: =Main!#REF! -> #REF! | E58: =Main!#REF! -> #REF! | F58: =Main!#REF! -> #REF! | G58: =Main!#REF! -> #REF!
A59: =Main!#REF! -> #REF! | B59: =Main!#REF! -> #REF! | C59: =Main!#REF! -> #REF! | D59: =Main!#REF! -> #REF! | E59: =Main!#REF! -> #REF! | F59: =Main!#REF! -> #REF! | G59: =Main!#REF! -> #REF!
A60: =Main!#REF! -> #REF! | B60: =Main!#REF! -> #REF! | C60: =Main!#REF! -> #REF! | D60: =Main!#REF! -> #REF! | E60: =Main!#REF! -> #REF! | F60: =Main!#REF! -> #REF! | G60: =Main!#REF! -> #REF!
A61: =Main!A47 -> Как называется наименьшая единица живого организма? | B61: =Main!B47 -> Ткань | C61: =Main!C47 -> Орган | D61: =Main!D47 -> Клетка | E61: =Main!E47 -> Система | F61: =Main!F47 -> 3 | G61: =Main!G47 -> Клетка является структурной и функциональной единицей всех живых организмов.
A62: =Main!#REF! -> #REF! | B62: =Main!#REF! -> #REF! | C62: =Main!#REF! -> #REF! | D62: =Main!#REF! -> #REF! | E62: =Main!#REF! -> #REF! | F62: =Main!#REF! -> #REF! | G62: =Main!#REF! -> #REF!
A63: =Main!A48 -> Кто является автором картины «Мона Лиза»? | B63: =Main!B48 -> Рафаэль | C63: =Main!C48 -> Микеланджело | D63: =Main!D48 -> Леонардо да Винчи | E63: =Main!E48 -> Тициан | F63: =Main!F48 -> 3 | G63: =Main!G48 -> Картина «Мона Лиза» была написана Леонардо да Винчи в начале XVI века и хранится в Лувре.
A64: =Main!A49 -> Какой материк пересекается экватором и нулевым меридианом? | B64: =Main!B49 -> Южная Америка | C64: =Main!C49 -> Африка | D64: =Main!D49 -> Австралия | E64: =Main!E49 -> Евразия | F64: =Main!F49 -> 2 | G64: =Main!G49 -> Африка — единственный материк, который пересекают и экватор, и нулевой меридиан.
A65: =Main!A50 -> Как называется основная денежная единица Европейского союза? | B65: =Main!B50 -> Доллар | C65: =Main!C50 -> Фунт | D65: =Main!D50 -> Евро | E65: =Main!E50 -> Франк | F65: =Main!F50 -> 3 | G65: =Main!G50 -> Евро был введен в безналичное обращение в 1999 году и используется в большинстве стран ЕС.
A66: =Main!A51 -> Кто открыл Америку в 1492 году? | B66: =Main!B51 -> Магеллан | C66: =Main!C51 -> Колумб | D66: =Main!D51 -> Кук | E66: =Main!E51 -> Веспуччи | F66: =Main!F51 -> 2 | G66: =Main!G51 -> Христофор Колумб достиг берегов Америки в 1492 году во время экспедиции под флагом Испании.
A67: =Main!A52 -> Как называется наука, изучающая происхождение слов? | B67: =Main!B52 -> Лингвистика | C67: =Main!C52 -> Филология | D67: =Main!D52 -> Этимология | E67: =Main!E52 -> Семантика | F67: =Main!F52 -> 3 | G67: =Main!G52 -> Этимология изучает происхождение слов, их первоначальное значение и изменения в языке со временем.
A68: =Main!A53 -> Какой художественный стиль характерен для работ Ван Гога? | B68: =Main!B53 -> Импрессионизм | C68: =Main!C53 -> Сюрреализм | D68: =Main!D53 -> Постимпрессионизм | E68: =Main!E53 -> Классицизм | F68: =Main!F53 -> 3 | G68: =Main!G53 -> Винсент Ван Гог считается представителем постимпрессионизма, направления конца XIX века, уделяющего внимание эмоциям и цвету.
A69: =Main!A54 -> Как называется прибор для наблюдения за удалёнными объектами в космосе? | B69: =Main!B54 -> Микроскоп | C69: =Main!C54 -> Бинокль | D69: =Main!D54 -> Телескоп | E69: =Main!E54 -> Спектрометр | F69: =Main!F54 -> 3 | G69: =Main!G54 -> Телескопы используются в астрономии для наблюдения планет, звёзд и галактик на больших расстояниях.
A70: =Main!A55 -> Какой газ используется в лампах дневного света? | B70: =Main!B55 -> Кислород | C70: =Main!C55 -> Аргон | D70: =Main!D55 -> Неон | E70: =Main!E55 -> Азот | F70: =Main!F55 -> 2 | G70: =Main!G55 -> В люминесцентных лампах применяется аргон, который помогает запускать электрический разряд.
A71: =Main!#REF! -> #REF! | B71: =Main!#REF! -> #REF! | C71: =Main!#REF! -> #REF! | D71: =Main!#REF! -> #REF! | E71: =Main!#REF! -> #REF! | F71: =Main!#REF! -> #REF! | G71: =Main!#REF! -> #REF!
A72: =Main!A56 -> Как называется система письма для слепых? | B72: =Main!B56 -> Морзе | C72: =Main!C56 -> Кириллица | D72: =Main!D56 -> Брайль | E72: =Main!E56 -> Латиница | F72: =Main!F56 -> 3 | G72: =Main!G56 -> Шрифт Брайля был разработан Луи Брайлем в XIX веке и основан на рельефных точках.
A73: =Main!#REF! -> #REF! | B73: =Main!#REF! -> #REF! | C73: =Main!#REF! -> #REF! | D73: =Main!#REF! -> #REF! | E73: =Main!#REF! -> #REF! | F73: =Main!#REF! -> #REF! | G73: =Main!#REF! -> #REF!
A74: =Main!#REF! -> #REF! | B74: =Main!#REF! -> #REF! | C74: =Main!#REF! -> #REF! | D74: =Main!#REF! -> #REF! | E74: =Main!#REF! -> #REF! | F74: =Main!#REF! -> #REF! | G74: =Main!#REF! -> #REF!
A75: =Main!A57 -> Как называется эпоха, последовавшая за Средневековьем? | B75: =Main!B57 -> Античность | C75: =Main!C57 -> Новое время | D75: =Main!D57 -> Просвещение | E75: =Main!E57 -> Возрождение | F75: =Main!F57 -> 2 | G75: =Main!G57 -> Новое время началось примерно в XV веке и связано с развитием науки, географическими открытиями и изменениями в обществе.
A76: =Main!#REF! -> #REF! | B76: =Main!#REF! -> #REF! | C76: =Main!#REF! -> #REF! | D76: =Main!#REF! -> #REF! | E76: =Main!#REF! -> #REF! | F76: =Main!#REF! -> #REF! | G76: =Main!#REF! -> #REF!
A77: =Main!A58 -> 0 | B77: =Main!B58 -> 0 | C77: =Main!C58 -> 0 | D77: =Main!D58 -> 0 | E77: =Main!E58 -> 0 | F77: =Main!F58 -> 0 | G77: =Main!G58 -> 0
A78: =Main!A59 -> 0 | B78: =Main!B59 -> 0 | C78: =Main!C59 -> 0 | D78: =Main!D59 -> 0 | E78: =Main!E59 -> 0 | F78: =Main!F59 -> 0 | G78: =Main!G59 -> 0
A79: =Main!A60 -> 0 | B79: =Main!B60 -> 0 | C79: =Main!C60 -> 0 | D79: =Main!D60 -> 0 | E79: =Main!E60 -> 0 | F79: =Main!F60 -> 0 | G79: =Main!G60 -> 0
A80: =Main!A61 -> 0 | B80: =Main!B61 -> 0 | C80: =Main!C61 -> 0 | D80: =Main!D61 -> 0 | E80: =Main!E61 -> 0 | F80: =Main!F61 -> 0 | G80: =Main!G61 -> 0
A81: =Main!A62 -> 0 | B81: =Main!B62 -> 0 | C81: =Main!C62 -> 0 | D81: =Main!D62 -> 0 | E81: =Main!E62 -> 0 | F81: =Main!F62 -> 0 | G81: =Main!G62 -> 0
A82: =Main!A63 -> 0 | B82: =Main!B63 -> 0 | C82: =Main!C63 -> 0 | D82: =Main!D63 -> 0 | E82: =Main!E63 -> 0 | F82: =Main!F63 -> 0 | G82: =Main!G63 -> 0
A83: =Main!A64 -> 0 | B83: =Main!B64 -> 0 | C83: =Main!C64 -> 0 | D83: =Main!D64 -> 0 | E83: =Main!E64 -> 0 | F83: =Main!F64 -> 0 | G83: =Main!G64 -> 0
A84: =Main!A65 -> 0 | B84: =Main!B65 -> 0 | C84: =Main!C65 -> 0 | D84: =Main!D65 -> 0 | E84: =Main!E65 -> 0 | F84: =Main!F65 -> 0 | G84: =Main!G65 -> 0
A85: =Main!A66 -> 0 | B85: =Main!B66 -> 0 | C85: =Main!C66 -> 0 | D85: =Main!D66 -> 0 | E85: =Main!E66 -> 0 | F85: =Main!F66 -> 0 | G85: =Main!G66 -> 0
A86: =Main!A67 -> 0 | B86: =Main!B67 -> 0 | C86: =Main!C67 -> 0 | D86: =Main!D67 -> 0 | E86: =Main!E67 -> 0 | F86: =Main!F67 -> 0 | G86: =Main!G67 -> 0
A87: =Main!A68 -> 0 | B87: =Main!B68 -> 0 | C87: =Main!C68 -> 0 | D87: =Main!D68 -> 0 | E87: =Main!E68 -> 0 | F87: =Main!F68 -> 0 | G87: =Main!G68 -> 0
A88: =Main!A69 -> 0 | B88: =Main!B69 -> 0 | C88: =Main!C69 -> 0 | D88: =Main!D69 -> 0 | E88: =Main!E69 -> 0 | F88: =Main!F69 -> 0 | G88: =Main!G69 -> 0
... A2001: =Main!A1982 -> 0 | B2001: =Main!B1982 -> 0 | C2001: =Main!C1982 -> 0 | D2001: =Main!D1982 -> 0 | E2001: =Main!E1982 -> 0 | F2001: =Main!F1982 -> 0 | G2001: =Main!G1982 -> 0
